altair/__init__.py
altair/_magics.py
altair/py.typed
altair/expr/__init__.py
altair/expr/consts.py
altair/expr/core.py
altair/expr/funcs.py
altair/jupyter/__init__.py
altair/jupyter/jupyter_chart.py
altair/jupyter/js/README.md
altair/jupyter/js/index.js
altair/utils/__init__.py
altair/utils/_dfi_types.py
altair/utils/_importers.py
altair/utils/_show.py
altair/utils/_transformed_data.py
altair/utils/_vegafusion_data.py
altair/utils/compiler.py
altair/utils/core.py
altair/utils/data.py
altair/utils/deprecation.py
altair/utils/display.py
altair/utils/execeval.py
altair/utils/html.py
altair/utils/mimebundle.py
altair/utils/plugin_registry.py
altair/utils/save.py
altair/utils/schemapi.py
altair/utils/selection.py
altair/utils/server.py
altair/utils/theme.py
altair/vegalite/__init__.py
altair/vegalite/api.py
altair/vegalite/data.py
altair/vegalite/display.py
altair/vegalite/schema.py
altair/vegalite/v5/__init__.py
altair/vegalite/v5/api.py
altair/vegalite/v5/compiler.py
altair/vegalite/v5/data.py
altair/vegalite/v5/display.py
altair/vegalite/v5/theme.py
altair/vegalite/v5/schema/__init__.py
altair/vegalite/v5/schema/channels.py
altair/vegalite/v5/schema/core.py
altair/vegalite/v5/schema/mixins.py
altair/vegalite/v5/schema/vega-lite-schema.json
altair_alx_alpha-5.4.1a0.dist-info/METADATA
altair_alx_alpha-5.4.1a0.dist-info/WHEEL
altair_alx_alpha-5.4.1a0.dist-info/licenses/LICENSE
altair_alx_alpha-5.4.1a0.dist-info/RECORD
